simple_multicall/__init__.py
simple_multicall/makerdao_multicall.py
simple_multicall/multicall.py
simple_multicall-0.1.5.dist-info/LICENSE
simple_multicall-0.1.5.dist-info/METADATA
simple_multicall-0.1.5.dist-info/WHEEL
simple_multicall-0.1.5.dist-info/top_level.txt
simple_multicall-0.1.5.dist-info/RECORD
