Metadata-Version: 2.1
Name: simple-multicall
Version: 0.1.5
Summary: Simple Web3 multicall
Author: Igor Lapshin
Author-email: igorlapshin@list.ru
License: MIT
Keywords: multicall,web3
Classifier: Development Status :: 3 - Alpha
Classifier: Intended Audience :: Developers
Classifier: License :: OSI Approved :: MIT License
Classifier: Natural Language :: English
Classifier: Programming Language :: Python :: 3
Requires: Web3
License-File: LICENSE
